setup.cfg
setup.py
rbcz/__init__.py
rbcz/account_movements_parser.py
rbcz/account_summary_parser.py
rbcz/movement.py
rbcz/rbcz.py
rbcz/statement.py
rbcz/statement_header_parser.py
rbcz/statement_parser.py
rbcz/utils.py
rbcz.egg-info/PKG-INFO
rbcz.egg-info/SOURCES.txt
rbcz.egg-info/dependency_links.txt
rbcz.egg-info/requires.txt
rbcz.egg-info/top_level.txt
rbcz/test/__init__.py
rbcz/test/test_import.py
rbcz/test/test_parse_header.py
rbcz/test/test_parse_individual_movement.py
rbcz/test/test_parse_statement.py
rbcz/test/test_parse_statements.py
rbcz/test/test_parse_summary.py