Metadata-Version: 1.1
Name: rbcz
Version: 0.6
Summary: library for interacting with Czech Raiffeisen Bank's text bank statements
Home-page: https://github.com/smcl/rbcz.py
Author: Sean McLemon
Author-email: sean.mclemon@gmail.com
License: UNKNOWN
Download-URL: https://github.com/smcl/rbcz.py/tarball/0.6
Keywords: banking,raiffeisen,czech,cz
Platform: UNKNOWN
